{
  "generated_at": "2026-06-21T15:04:05+09:00",
  "risk_regime": {
    "regime": "RISK_ON",
    "confidence": "MID",
    "rationale": "米・イラン停戦合意（6/14発表→6/19スイス署名）でホルムズ海峡が完全再開通、WTI原油が76ドル台へ急落しインフレ懸念が大幅に後退。AI・半導体株主導の株高が日米市場を押し上げ、日経225は6/16に70,000円を初突破し6/19に71,952円の史上最高値を更新後、6/21は71,250円で引け（週間+8%超）。ただしFRBが6/17会合でウォーシュ新議長主導のタカ派シフト（2026年内追加利上げを9名が支持、年末FF金利中央値3.8%に上方修正）を打ち出しており、長期金利高止まりとドル高がリスク資産の上値を抑制する可能性がある。全体としてリスクオン優位だが、和平の持続性とFRBの追加引き締め不確実性が共存する段階。",
    "key_drivers": [
      "米・イラン停戦合意発効（6/19スイス署名）でホルムズ海峡60日再開、WTI原油が76ドル台へ急落",
      "AI・半導体株主導の株高が継続、日経225が6/16に史上初の70,000円突破・6/19に71,952円ATH",
      "FRBが6/17会合で利上げ据え置きもタカ派シフト（2026年内追加利上げ9名支持、年末中央値3.8%）",
      "日銀が6/16に25bp利上げで政策金利1.0%（1995年以来最高）、政府は11.7兆円介入も円安継続",
      "ECBが6/11に3年ぶりの利上げ（+25bp→2.25%）、主要中銀の引き締め圧力が金融環境を引き締め方向に"
    ]
  },
  "assets": [
    {
      "name": "日経225",
      "ticker": "NKD=F",
      "bias": "BULLISH",
      "conviction": "MID",
      "rationale": "6/16に70,000円を史上初突破、6/19に71,952円の史上最高値を更新。6/21（金）は71,250円で引け、週間では+8%超の大幅上昇。AI・半導体関連株（東京エレクトロン一時+14%、アドバンテスト+5.5%）がけん引し、米・イラン停戦による地政学リスク後退・原油安がコスト低下期待を追い風に。外国人投資家の日本株買い継続（2025年4月以来16兆円流入）、年初来+33%。ただし史上最高値圏でのPER拡大（高値警戒）と、日銀利上げ継続・円高再浮上リスク、実弾介入への警戒が上値を抑制。",
      "catalysts": [
        "AI・半導体需要拡大による東京エレクトロン・アドバンテスト等の業績上方修正期待",
        "米・イラン停戦合意による地政学プレミアム解消と原油安によるコスト改善",
        "外国人投資家の日本株買い継続（2025年4月以来16兆円流入）",
        "ドル円160-161円台の円安持続が輸出企業の収益を下支え",
        "財務省・日銀の為替介入・追加利上げ観測が急速な円高リスクとなり上値を抑制"
      ],
      "top_news": [
        {
          "headline": "日経225が6月19日に71,952円の史上最高値を更新—バブル崩壊後の最高値を大幅に更新",
          "published": "2026-06-19",
          "comment": "停戦期待と半導体株高が重なり史上最高値更新、週足では年初来最大級の上げ幅",
          "source": "Japan Times / TradingKey",
          "tier": 2,
          "credibility": "HIGH",
          "corroborated_by": ["Japan Times", "FXEmpire", "Al Jazeera", "TradingKey"],
          "materiality": "high",
          "direction": "bullish",
          "url": "https://www.japantimes.co.jp/business/2026/06/16/markets/nikkei-70000-first-time-june/"
        },
        {
          "headline": "東京エレクトロンが一時+14%急騰、アドバンテストも+5.5%—AI半導体需要が日経を牽引",
          "published": "2026-06-16",
          "comment": "半導体製造装置大手2社の急騰が日経の主要牽引役、AI投資サイクルの継続を示唆",
          "source": "TradingKey / FXEmpire",
          "tier": 2,
          "credibility": "HIGH",
          "corroborated_by": ["KuCoin", "Japan Times"],
          "materiality": "high",
          "direction": "bullish",
          "url": "https://www.tradingkey.com/analysis/stocks/more/261969204-japan-nikkei225-70000-tradingkey"
        },
        {
          "headline": "日経225が6月21日（金）は71,250円で引け、週間+8%超と今年最大級の週足上昇",
          "published": "2026-06-21",
          "comment": "週足で8%超と年初来最大級。高値水準での過熱感には引き続き注意が必要",
          "source": "Investtech / Trading Economics",
          "tier": 3,
          "credibility": "MID",
          "corroborated_by": ["Trading Economics"],
          "materiality": "high",
          "direction": "bullish",
          "url": "https://tradingeconomics.com/japan/stock-market"
        }
      ]
    },
    {
      "name": "S&P500",
      "ticker": "ES=F",
      "bias": "BULLISH",
      "conviction": "MID",
      "rationale": "S&P500先物（ES=F）は7,556付近で推移し、地政学リスク後退・原油安・AI株高の追い風でリスクオン優勢。週間でも堅調な推移。ただしFRBが6/17会合でタカ派シフト（2026年内追加利上げを9名支持、コアPCE年末見通し3.6%に上方修正）を鮮明にしており、長期金利の高止まりと高バリュエーションへの圧力がある。短期的な上値余地は限られつつも基調は強気。",
      "catalysts": [
        "中東地政学リスク後退（米・イラン停戦）によるセンチメント改善と原油安",
        "AI・半導体関連株の継続的な業績拡大期待",
        "FRB追加利上げ示唆による長期金利上昇・バリュエーション圧迫リスク",
        "コアPCE見通し3.6%への上方修正が根強いインフレ・スタグフレーション懸念を示す"
      ],
      "top_news": [
        {
          "headline": "FRBが6月会合で政策金利（3.50-3.75%）を据え置き、ただし9名が2026年内追加利上げを支持",
          "published": "2026-06-17",
          "comment": "利上げ見送りでも年内追加利上げを多数が支持、ドル高・金利高止まりで株の上値が重くなりやすい",
          "source": "CNBC",
          "tier": 2,
          "credibility": "HIGH",
          "corroborated_by": ["Advisor Perspectives", "Kiplinger", "Charles Schwab", "Federal Reserve"],
          "materiality": "high",
          "direction": "bearish",
          "url": "https://www.cnbc.com/2026/06/17/fed-interest-rate-decision-june-2026.html"
        },
        {
          "headline": "S&P500先物が7,556付近で推移、米・イラン停戦と半導体株高がサポート",
          "published": "2026-06-21",
          "comment": "リスクオン継続も、FRBのタカ派シフトが上値余地を限定する局面",
          "source": "Investing.com / CME Group",
          "tier": 2,
          "credibility": "MID",
          "corroborated_by": ["CME Group"],
          "materiality": "mid",
          "direction": "bullish",
          "url": "https://www.investing.com/indices/us-spx-500-futures"
        },
        {
          "headline": "FOMCドット・チャート：2026年末FF金利中央値を3.8%に上方修正、コアPCE見通しも3.6%へ",
          "published": "2026-06-17",
          "comment": "インフレ長期化見通しの上方修正は株式市場に中期的な逆風、利上げ再開なら要注意",
          "source": "Advisor Perspectives / CNBC",
          "tier": 2,
          "credibility": "HIGH",
          "corroborated_by": ["CNBC", "Federal Reserve"],
          "materiality": "high",
          "direction": "bearish",
          "url": "https://www.advisorperspectives.com/dshort/updates/2026/06/18/feds-interest-rate-decision-june-17-2026"
        }
      ]
    },
    {
      "name": "ナスダック",
      "ticker": "NQ=F",
      "bias": "BULLISH",
      "conviction": "MID",
      "rationale": "AI・半導体株高がナスダックを力強く支えており、基調はリスクオン。日経AI株の急騰（東京エレクトロン+14%等）はナスダック関連銘柄の需要継続を示唆。ただしFRBのタカ派シフトにより長期金利が高止まりし、高成長株のバリュエーション圧迫が懸念される。AI投資サイクルの継続が確認されるうちは強気バイアス優勢。",
      "catalysts": [
        "AI・半導体企業（NVIDIA等）の継続的な業績成長と設備投資需要の拡大",
        "米・イラン停戦によるセンチメント改善と原油安による技術企業コスト低下",
        "FRB追加利上げ示唆による長期金利上昇リスク（高PER成長株バリュエーションへの逆風）"
      ],
      "top_news": [
        {
          "headline": "AI・半導体関連株の業績拡大がナスダックを支え、S&P500と歩調を合わせ週間上昇",
          "published": "2026-06-21",
          "comment": "AI投資サイクルが続く限りナスダック強気材料が続く、ただし高金利リスクと共存",
          "source": "IG Markets / Al Jazeera",
          "tier": 2,
          "credibility": "MID",
          "corroborated_by": ["Al Jazeera", "FXEmpire"],
          "materiality": "mid",
          "direction": "bullish",
          "url": "https://www.aljazeera.com/economy/2026/6/3/japans-stock-market-hits-new-record-as-ai-boom-gathers-steam"
        },
        {
          "headline": "FRBが2026年内追加利上げ示唆、長期金利高止まりで成長株バリュエーション圧迫",
          "published": "2026-06-17",
          "comment": "高金利は高PER成長株の割引率を高め、ナスダック構成銘柄の下押し圧力になりやすい",
          "source": "CNBC",
          "tier": 2,
          "credibility": "HIGH",
          "corroborated_by": ["Kiplinger", "Advisor Perspectives", "Federal Reserve"],
          "materiality": "mid",
          "direction": "bearish",
          "url": "https://www.cnbc.com/2026/06/17/fed-interest-rate-decision-june-2026.html"
        }
      ]
    },
    {
      "name": "金",
      "ticker": "GC=F",
      "bias": "NEUTRAL",
      "conviction": "MID",
      "rationale": "1月28日の史上最高値5,589ドル/オンスから6月中旬には4,172ドル付近まで約25%下落。米・イラン停戦合意で地政学的安全資産需要が後退し、リスクオン環境と原油安が重石。FRBのタカ派姿勢による実質金利上昇・ドル高も圧迫要因。一方、中央銀行の年間755トン規模の購入需要（Q1実績244トン）と中国の輸入急増（Q1：317トン＝前四半期比3倍）が底値を支え、JPモルガンは年末6,000ドル予測を維持。強弱材料が均衡しNEUTRAL。",
      "catalysts": [
        "中央銀行の継続的な購入需要（2026年通年755トン予測、Q1実績244トン）が長期的な下支え",
        "中国の金輸入量がQ1に前四半期比3倍の317トンに急増",
        "米・イラン停戦合意による安全資産需要の後退がショートタームでの重石",
        "FRBのタカ派シフトによる実質金利上昇・ドル高圧力"
      ],
      "top_news": [
        {
          "headline": "金が1月の史上最高値5,589ドルから4,172ドルへ約25%下落、停戦でリスクオン転換が重石に",
          "published": "2026-06-14",
          "comment": "停戦期待で安全資産需要が一服、ただし中央銀行の継続購入が下支えになりやすい",
          "source": "Capital.com / World Gold Council",
          "tier": 2,
          "credibility": "MID",
          "corroborated_by": ["World Gold Council", "J.P. Morgan"],
          "materiality": "high",
          "direction": "bearish",
          "url": "https://capital.com/en-int/market-updates/gold-price-forecast-02-06-2026"
        },
        {
          "headline": "JPモルガン、金の年末6,000ドル予測を維持—中央銀行が記録的な高値でも購入継続",
          "published": "2026-06-01",
          "comment": "中銀の大量購入が中長期的な金価格を支えるとの見方で、下落局面での底堅さを示す",
          "source": "J.P. Morgan Global Research",
          "tier": 1,
          "credibility": "HIGH",
          "corroborated_by": ["World Gold Council", "ING THINK", "isabullion"],
          "materiality": "mid",
          "direction": "bullish",
          "url": "https://www.jpmorgan.com/insights/global-research/commodities/gold-prices"
        },
        {
          "headline": "世界金需要レポートQ1 2026：中央銀行が244トン純買い、中国輸入317トンと前四半期比3倍",
          "published": "2026-05-15",
          "comment": "中国と新興国中銀の構造的な金需要が続いており、価格の長期的な下支えとなっている",
          "source": "World Gold Council",
          "tier": 1,
          "credibility": "HIGH",
          "corroborated_by": ["J.P. Morgan", "ING"],
          "materiality": "mid",
          "direction": "bullish",
          "url": "https://www.gold.org/goldhub/research/gold-demand-trends/gold-demand-trends-q1-2026"
        }
      ]
    },
    {
      "name": "原油",
      "ticker": "CL=F",
      "bias": "BEARISH",
      "conviction": "HIGH",
      "rationale": "6/14の米・イラン停戦合意発表でWTIが約5.8%急落し76ドル台に（Brentも78.96ドル、3月以来初めて80ドル割れ）。ホルムズ海峡の完全再開通とイランへの制裁解除で即時輸出再開が決定。滞留タンカーから推定1億バレル規模の供給増が今後3〜6か月で市場に流入する見通し。需給緩和により当面は下押し圧力が続くと見る。ただし地政学の不確実性（イスラエル・核問題）や生産再開ペース次第で下げが一服する可能性も残る。",
      "catalysts": [
        "米・イラン停戦合意発効でホルムズ海峡が無条件再開通、イラン産原油の即時輸出再開",
        "滞留タンカー約1億バレル分の供給が今後3〜6か月で市場に流入する見通し",
        "イラン核問題・イスラエルの懐疑論が残存し、和平破綻時の急反騰リスクが尾を引く"
      ],
      "top_news": [
        {
          "headline": "米・イラン停戦合意（6/14発表→6/19スイス署名）でWTIが5.8%急落、76ドル台・3か月ぶり安値",
          "published": "2026-06-14",
          "comment": "停戦合意でイラン産原油の供給再開が確定、需給緩和で原油価格に強い下押し圧力が生じた",
          "source": "CNN Business / CNBC / Axios",
          "tier": 2,
          "credibility": "HIGH",
          "corroborated_by": ["CNN Business", "CNBC", "Axios", "Al Jazeera", "NBC News"],
          "materiality": "high",
          "direction": "bearish",
          "url": "https://www.cnbc.com/2026/06/16/us-iran-peace-agreement-oil-prices-tankers-strait-of-hormuz-transit.html"
        },
        {
          "headline": "Brentが80ドル割れ、3月以来初めて—ホルムズ海峡再開通で供給拡大期待が主導",
          "published": "2026-06-16",
          "comment": "国際原油指標が80ドルを割り込んだことでインフレ懸念が後退、株・景気にはプラス材料",
          "source": "CNBC",
          "tier": 2,
          "credibility": "HIGH",
          "corroborated_by": ["CNN Business", "Axios"],
          "materiality": "high",
          "direction": "bearish",
          "url": "https://www.cnbc.com/2026/06/16/us-iran-peace-agreement-oil-prices-tankers-strait-of-hormuz-transit.html"
        },
        {
          "headline": "滞留タンカーから1億バレル規模の供給増、本格流入まで3〜6か月—油価の下げが持続しやすい環境",
          "published": "2026-06-16",
          "comment": "一時的な大量供給で需給が緩み、短中期的に原油安が持続しやすい構造になった",
          "source": "NBC News",
          "tier": 2,
          "credibility": "MID",
          "corroborated_by": ["CNN Business"],
          "materiality": "high",
          "direction": "bearish",
          "url": "https://www.nbcnews.com/business/markets/oil-prices-iran-deal-hormuz-doubts-rcna350087"
        }
      ]
    },
    {
      "name": "ドル円",
      "ticker": "USDJPY",
      "bias": "BULLISH",
      "conviction": "MID",
      "rationale": "日銀が6/16に25bp利上げし1.0%（1995年以来最高）に引き上げ、政府が11.7兆円超（約735億ドル）規模の為替介入を実施したにもかかわらず、ドル円は160〜161円台の高水準で高止まり。日米金利差（米3.5-3.75% vs 日1.0%）が円キャリートレードを維持し、FRBウォーシュ新議長のタカ派転換がドル買い需要を高めている。日本10年JGB金利（2.64%）と米10年債（4.45%）の大きな開きがドル高・円安を構造的に支持。再介入リスクが突発的な円高を引き起こす可能性があり、上値は不安定。",
      "catalysts": [
        "日米金利差の縮小が限定的（米3.5-3.75% vs 日1.0%）でキャリートレード継続",
        "FRBウォーシュ議長の タカ派シフトと2026年内追加利上げ示唆によるドル買い",
        "日銀の1.0%利上げと政府の11.7兆円介入の円安阻止効果が限定的",
        "日本10年JGB(2.64%) vs 米10年債(4.45%)の1.81%の金利差がキャリー需要を下支え",
        "財務省・日銀の追加介入・日銀追加利上げ観測が突発的な円高リスクとして存在"
      ],
      "top_news": [
        {
          "headline": "日銀が政策金利を1.0%に引き上げ、1995年以来の最高水準—ドル円は160円台高止まり",
          "published": "2026-06-16",
          "comment": "利上げにもかかわらず日米金利差が大きく円安継続、追加介入があれば急騰に注意",
          "source": "CNBC",
          "tier": 2,
          "credibility": "HIGH",
          "corroborated_by": ["Japan Times", "Investing.com", "Trading Economics"],
          "materiality": "high",
          "direction": "neutral",
          "url": "https://www.cnbc.com/2026/06/16/boj-rate-hike-historic-inflation.html"
        },
        {
          "headline": "日本政府が11.7兆円超の為替介入を実施も効果限定的、ドル円160〜161円台を維持",
          "published": "2026-06-19",
          "comment": "大規模介入後もドル高圧力が優勢、米金利の高止まりが円安の根本要因として続く",
          "source": "CNBC",
          "tier": 2,
          "credibility": "HIGH",
          "corroborated_by": ["Japan Times"],
          "materiality": "high",
          "direction": "bullish",
          "url": "https://www.cnbc.com/amp/2026/06/19/japan-yen-intervention-boj-rate-hike.html"
        },
        {
          "headline": "FRBウォーシュ新議長体制でタカ派シフト、ユーロドル急落・ドル全面高の展開",
          "published": "2026-06-17",
          "comment": "新FRB議長の強硬姿勢がドル買いを加速、ドル円の上昇圧力が当面継続しやすい",
          "source": "Investing.com / FXStreet",
          "tier": 2,
          "credibility": "MID",
          "corroborated_by": ["Investing.com", "FXStreet"],
          "materiality": "mid",
          "direction": "bullish",
          "url": "https://www.investing.com/analysis/usdjpy-eurusd-outlook-a-different-fed-changes-the-fx-outlook-200682369"
        }
      ]
    },
    {
      "name": "ユーロドル",
      "ticker": "EURUSD",
      "bias": "BEARISH",
      "conviction": "MID",
      "rationale": "FRBウォーシュ新議長就任後のタカ派転換を受け、EUR/USDは1.1417付近まで急落（3月以来の安値）。米国の2026年内追加利上げ観測が強まる一方、ECBが6/11に+25bpの利上げを実施（→2.25%）したものの欧州スタグフレーション懸念がユーロの反発を抑制。ドル高圧力が当面継続しやすい環境。ただしリスクオン継続・米国の貿易赤字拡大がドル独歩高の持続性に疑問を呈しており、下落トレンドの強さはMID。",
      "catalysts": [
        "FRBウォーシュ議長のタカ派シフトと2026年内追加利上げ示唆によるドル高",
        "米欧金融政策の方向性の乖離（FRB利上げ方向 vs ECBの利上げ打ち止め懸念）",
        "ECBが6/11に+25bp利上げ（→2.25%）もイラン戦争由来のエネルギー高騰でユーロ圏スタグフレーション懸念",
        "リスクオン継続によるドル安全資産需要の相対的低下が若干ユーロを支える可能性"
      ],
      "top_news": [
        {
          "headline": "ユーロドルが1.1417に急落、FRBウォーシュ議長の初会合でタカ派シフト明確化—3月以来の安値",
          "published": "2026-06-17",
          "comment": "新FRB議長の強硬姿勢でドル全面高、ユーロドルは3月以来の安値圏に押し込まれた",
          "source": "Investing.com",
          "tier": 2,
          "credibility": "MID",
          "corroborated_by": ["FXStreet", "forex.com"],
          "materiality": "high",
          "direction": "bearish",
          "url": "https://www.investing.com/analysis/usdjpy-eurusd-outlook-a-different-fed-changes-the-fx-outlook-200682369"
        },
        {
          "headline": "ECBが3年ぶりの利上げ（+25bp→2.25%）、イラン戦争由来のエネルギー高騰でスタグフレーション対応",
          "published": "2026-06-11",
          "comment": "ECBも利上げを余儀なくされたが欧州景気への悪影響懸念が残り、ユーロの反発力は限定的",
          "source": "Reuters / Bloomberg",
          "tier": 2,
          "credibility": "HIGH",
          "corroborated_by": ["Bloomberg", "Reuters"],
          "materiality": "mid",
          "direction": "neutral",
          "url": "https://www.investing.com/analysis/usdjpy-eurusd-outlook-a-different-fed-changes-the-fx-outlook-200682369"
        }
      ]
    },
    {
      "name": "ビットコイン",
      "ticker": "BTC-USD",
      "bias": "NEUTRAL",
      "conviction": "LOW",
      "rationale": "BTCは63,675ドル付近（6/20時点）で推移。1月の史上最高値126,000ドルから約50%の大幅下落後、65,000〜72,500ドルのレンジで推移。RSIが40台（ニュートラル寄りの弱含み）で、テクニカル指標はベア20 vs ブル10と弱め。リスクオン環境でも反発力が鈍く、ナスダックとの相関（約85%）を勘案するとAI株高の恩恵が部分的に及ぶ可能性があるが、上値は重い。方向感に乏しく低コンビクション。",
      "catalysts": [
        "リスクオン環境（株高・原油安）がBTC反発の間接的な追い風",
        "テクニカル指標がベア優勢（ベア20 vs ブル10）、RSI40台で上値重し",
        "1月高値126,000ドルから約50%下落後の底値固め局面、レンジ推移で方向感喪失",
        "65,000ドル超えの定着がなければトレンド転換は確認できない"
      ],
      "top_news": [
        {
          "headline": "ビットコインが63,675ドル付近で推移、1月高値の約12.6万ドルから50%超の下落",
          "published": "2026-06-20",
          "comment": "リスクオン環境でも反発が鈍く、テクニカルはベア優勢で方向感が定まらない状況",
          "source": "CoinDCX / Coinbase / Yahoo Finance",
          "tier": 3,
          "credibility": "MID",
          "corroborated_by": ["Yahoo Finance", "CoinDesk"],
          "materiality": "mid",
          "direction": "bearish",
          "url": "https://www.coinbase.com/price/bitcoin"
        },
        {
          "headline": "BTC-RSIが40台でニュートラル、テクニカル指標はベア20 vs ブル10と弱気優勢",
          "published": "2026-06-21",
          "comment": "技術的には下降圧力が残存、65,000ドルを明確に超えるまでは慎重なスタンスが妥当",
          "source": "CoinDCX",
          "tier": 3,
          "credibility": "LOW",
          "corroborated_by": [],
          "materiality": "mid",
          "direction": "bearish",
          "url": "https://coindcx.com/blog/price-predictions/bitcoin-price-weekly/"
        }
      ]
    }
  ],
  "discarded": [
    {
      "headline": "マイク・マクグローン氏、BTC98,000ドル・金5,500ドル・原油120ドルを2026年に予測",
      "reason": "単一アナリストの予測値で独立した裏付けなし。現実の市況（原油76ドル、金4,172ドル、BTC6.3万ドル）と大きく乖離しており信頼性LOW、除外"
    },
    {
      "headline": "ビットコインが6月23日に65,367ドルに上昇するとの予測",
      "reason": "単一サイト（CoinDCX）の短期価格予測モデルで独立した裏付けなし。価格予言は根拠に乏しいためLOWと判定し除外"
    },
    {
      "headline": "2026年株式指数見通し：ダウ・日経・ハンセンが優位（2025年末時点の予測）",
      "reason": "2025年末時点の年初予測であり情報が古い。現在の市況を反映していないため除外"
    },
    {
      "headline": "イスラエルの和平懐疑論と核・制裁問題が6/19-20に台頭し市場が反落（前回ブリーフィングの核心材料）",
      "reason": "6/21の最新動向では米・イラン停戦が6/19のスイス署名で進展し、週次では株高・原油安が持続。懐疑論は依然リスクとして残るが、本ブリーフィングでは現状の主要材料として統合済み"
    }
  ]
}
