{
  "generated_at": "2026-06-04T15:10:00+09:00",
  "risk_regime": {
    "regime": "RISK_OFF",
    "confidence": "MID",
    "rationale": "2月28日開始の米・イスラエル対イラン軍事行動によりホルムズ海峡閉鎖が継続し、IEAが「史上最大の石油供給途絶」と認定。WTI原油は$95台で3日続伸しエネルギー主導のインフレがFRBの利下げ余地を削っている。6月3日にはBTCが$72,000台から$66,965まで急落し、仮想通貨恐怖&強欲指数は11（極度の恐怖）。日銀は6月15-16日会合で0.75%→1.0%への利上げが市場織り込み78-81%、ドル円は159.9円の介入警戒ゾーンに滞在。一方でS&P500は6月2日に7,600を初突破（年初来24回目の最高値）、NvidiaのVera Rubin量産やMarvell+22%急騰など半導体・AI銘柄が相場を下支えし、全面リスクオフには至っていない。地政学リスクとインフレ再燃が主因でRISK_OFFと判断するが、AI収益モメンタムが拮抗するためMID confidence。",
    "key_drivers": [
      "ホルムズ海峡閉鎖継続（2月28日以降）—IEAが「史上最大の供給途絶」と認定、WTI$95台で3日続伸",
      "BTCが$72,000台から$67,000割れへ急落—Strategy4年ぶり売却・現物ETF月間$24億（年間最大）流出",
      "日銀6月15-16日会合での0.75%→1.0%利上げ確率78-81%—ドル円159.9円と介入警戒ゾーン",
      "米ミシガン大消費者信頼感指数が過去最低水準に急落—エネルギー高騰による生活コスト圧迫が主因",
      "S&P500は6月2日に7,600を初突破（AI/半導体主導）—全面崩落を防ぐ下支え要因"
    ]
  },
  "assets": [
    {
      "name": "日経225",
      "ticker": "NKD=F",
      "bias": "NEUTRAL",
      "conviction": "MID",
      "rationale": "6月3日（水）に68,000台を初めて突破する最高値を記録したが、6月4日（木）は地政学リスクと米イラン緊張の高まりを受けて1.5%下落し67,000台に反落。SoftBank Group（-7.8%）、藤倉コンポジット（-6.1%）、村田製作所（-2.9%）など技術株が主導した下落。円安（ドル円159円台）が輸出企業を支援する一方、6月16日の日銀会合（利上げ確率78-81%）が最大の不確実性。利上げ実施なら円高→輸出株売りへの転換リスクがあり、強気・弱気要因が拮抗してNEUTRAL。",
      "catalysts": [
        "6月15-16日の日銀政策決定会合—0.75%→1.0%利上げ確率78-81%、実施なら円高・輸出株安リスク",
        "ドル円が159〜160円台と介入警戒ゾーン—突発的な円高リスクが輸出株の頭を抑える",
        "SoftBank AIプラットフォーム発表が直前の上昇を牽引したが急落でアク抜け局面の可能性",
        "中東紛争によるエネルギー輸入コスト高—日本の貿易赤字拡大と企業収益への下押し圧力"
      ],
      "top_news": [
        {
          "headline": "日経225が68,000台を初突破後に1.5%反落—中東情勢と技術株売りで67,000台に",
          "published": "2026-06-04",
          "comment": "記録更新後の急落で、中東リスクが日本株の上値を抑える要因として再認識された",
          "source": "BBN Times",
          "tier": 3,
          "credibility": "MID",
          "corroborated_by": [],
          "materiality": "high",
          "direction": "bearish",
          "url": "https://www.bbntimes.com/financial/nikkei-225-tokyo-index-surges-0-91-to-66-934-as-softbank-ai-announcement-and-semiconductor-demand-drive-japan-equities-higher"
        },
        {
          "headline": "日銀6月15-16日会合での追加利上げ確率が78-81%に上昇—円相場159.9円と介入ライン接近",
          "published": "2026-06-03",
          "comment": "利上げ実施なら円高が進み輸出株の売り圧力となるが、インフレ抑制には必要な措置",
          "source": "cryptobriefing.com",
          "tier": 3,
          "credibility": "MID",
          "corroborated_by": ["CNBC", "Reuters"],
          "materiality": "high",
          "direction": "bearish",
          "url": "https://cryptobriefing.com/yen-intervention-risk-boj-rate-hike/"
        },
        {
          "headline": "日本当局が4月28日〜5月27日に約11.7兆円（約736億ドル）の為替介入を実施—史上最大規模",
          "published": "2026-05-27",
          "comment": "史上最大規模の介入でも160円接近が続いており、円安圧力の根強さを示す",
          "source": "CNBC",
          "tier": 2,
          "credibility": "HIGH",
          "corroborated_by": ["Reuters"],
          "materiality": "mid",
          "direction": "bearish",
          "url": "https://www.cnbc.com/2026/05/07/japan-yen-intervention-boj-rate-gap-currency-pressure.html"
        }
      ]
    },
    {
      "name": "S&P500",
      "ticker": "ES=F",
      "bias": "BULLISH",
      "conviction": "MID",
      "rationale": "6月2日に7,617.66の史上最高値（年初来24回目の最高値、初の7,600超え）を記録。Marvell+22%、HPE+30%など半導体・AIインフラ株が牽引。Goldman Sachsが年末目標を8,000に引き上げ。ただし市場内訳は脆弱で、インデックスを上回るのは構成銘柄の約17%のみ（10年来最低水準）。6月3日はBroadcom等の決算前で小幅調整。エネルギー高騰によるインフレ再燃とFRB利下げ後退観測が下押しリスクとして意識される。",
      "catalysts": [
        "AI/半導体の収益加速：Nvidia Vera Rubin量産開始（6月）、Marvell+22%・HPE+30%急騰",
        "Goldman SachsがS&P500年末目標を8,000に引き上げ（従来目標7,600から）",
        "FOMCは6月16-17日会合で据え置き見込み（確率96%）—突発的利上げリスクは低い",
        "米ミシガン大消費者信頼感が過去最低—エネルギー高騰で実体消費が圧迫され下押しリスク継続"
      ],
      "top_news": [
        {
          "headline": "S&P500が6月2日に7,617.66の史上最高値—AI・半導体主導で年初来24回目の最高値を更新",
          "published": "2026-06-02",
          "comment": "市場の主役はAI関連株で、幅広い銘柄への波及は限定的であることに注意が必要",
          "source": "TheStreet",
          "tier": 2,
          "credibility": "HIGH",
          "corroborated_by": ["CNBC", "Motley Fool"],
          "materiality": "high",
          "direction": "bullish",
          "url": "https://www.thestreet.com/stock-market-today/stock-market-today-dow-jones-sp-500-nasdaq-updates-june-02-2026"
        },
        {
          "headline": "Goldman Sachsが2026年末のS&P500目標を8,000に引き上げ—AIインフラ投資の継続を評価",
          "published": "2026-06-02",
          "comment": "大手証券の目標引き上げは強気相場を後押しするが、楽観が行き過ぎるリスクも伴う",
          "source": "unboxfuture.com",
          "tier": 3,
          "credibility": "MID",
          "corroborated_by": [],
          "materiality": "mid",
          "direction": "bullish",
          "url": "https://www.unboxfuture.com/2026/06/the-tech-led-s-500-surge-inside.html?m=1"
        },
        {
          "headline": "米ミシガン大消費者信頼感指数が過去最低水準に急落—イラン戦争によるエネルギー高騰が主因",
          "published": "2026-06-01",
          "comment": "生活コスト上昇が実体消費を圧迫し始め、株高と景気実態の乖離が広がるリスクがある",
          "source": "J.P. Morgan",
          "tier": 2,
          "credibility": "MID",
          "corroborated_by": [],
          "materiality": "mid",
          "direction": "bearish",
          "url": "https://www.jpmorgan.com/content/dam/jpmorgan/documents/wealth-management/mid-year-outlook-2026.pdf"
        }
      ]
    },
    {
      "name": "ナスダック",
      "ticker": "NQ=F",
      "bias": "BULLISH",
      "conviction": "MID",
      "rationale": "6月2日に27,093の史上最高値圏で推移。Nvidia次世代「Vera Rubin」が6月に量産入りし、AI需要継続性が確認された。半導体ETF（SOX）への資金流入が旺盛で海外機関投資家の買いも続く。ただしS&P500同様に上昇は少数銘柄に集中（構成銘柄の約17%のみがインデックス超え）。FRB利下げ期待後退がグロース株のバリュエーション調整リスクとなり、地政学リスクが高まった際の下落幅も大きい。6月3日はBroadcom・CrowdStrikeの決算前で小幅調整。",
      "catalysts": [
        "Nvidia Vera Rubinプラットフォームが6月に量産開始—AIデータセンター投資サイクルの継続を確認",
        "Broadcom・CrowdStrikeの6月3日決算発表—AI関連株の次の方向感を左右する重要イベント",
        "FRB利下げ期待後退（インフレ再燃）—グロース株のバリュエーション調整リスクが内在",
        "AI/半導体関連のエンタープライズ需要がハイパースケーラー以外にも波及—裾野拡大の兆し"
      ],
      "top_news": [
        {
          "headline": "ナスダックが最高値圏27,093で推移—Nvidia Vera Rubin量産開始でAI需要の持続性を確認",
          "published": "2026-06-02",
          "comment": "AI投資サイクルが続いている証拠だが、少数銘柄への集中は市場脆弱性でもある",
          "source": "CNBC",
          "tier": 2,
          "credibility": "HIGH",
          "corroborated_by": ["TheStreet"],
          "materiality": "high",
          "direction": "bullish",
          "url": "https://www.cnbc.com/2026/06/01/stock-market-today-live-updates.html"
        },
        {
          "headline": "Marvellが+22%急騰—NvidiaのJensen Huang CEOが「次の兆ドル企業候補」と言及",
          "published": "2026-06-02",
          "comment": "特定の発言が株価を大きく動かす相場。AI関連株の乱高下リスクも高まっている",
          "source": "Saxo Bank",
          "tier": 2,
          "credibility": "MID",
          "corroborated_by": [],
          "materiality": "mid",
          "direction": "bullish",
          "url": "https://www.home.saxo/en-gb/content/articles/options/options-brief---chip-surge-new-sp-record---3-june-2026-03062026"
        },
        {
          "headline": "HPEが+30%急騰—AIを活用したガイダンス大幅引き上げを発表",
          "published": "2026-06-02",
          "comment": "AIインフラ需要がエンタープライズ全体に広がりつつあり、裾野拡大の兆しが見える",
          "source": "TheStreet",
          "tier": 2,
          "credibility": "HIGH",
          "corroborated_by": ["Motley Fool"],
          "materiality": "mid",
          "direction": "bullish",
          "url": "https://www.thestreet.com/stock-market-today/stock-market-today-dow-jones-sp-500-nasdaq-updates-june-02-2026"
        }
      ]
    },
    {
      "name": "金",
      "ticker": "GC=F",
      "bias": "BULLISH",
      "conviction": "MID",
      "rationale": "6月4日現在$4,436.64/ozで推移。イラン戦争による地政学的リスクプレミアムが年初来リターンの約12%分を占め、主要中央銀行による継続的な買い付け（2026年見込み約755トン）が下支え。JPMorganは2026年Q4平均$5,055/oz・2027年末$5,400/ozを予測。短期（1週間）の予測は-1.08%と調整圧力もあり。FRBの利下げ期待後退が実質金利を押し上げ金利機会コストが増す局面では逆風となり得るが、中長期は強気スタンスを維持。",
      "catalysts": [
        "イラン戦争継続によるリスクプレミアム—世界最大規模の供給途絶が安全資産需要を維持",
        "主要中央銀行が2026年も約755トンの金購入を見込む—2022年以前の平均を大幅上回る水準",
        "JPMorganが2026年Q4平均$5,055/ozを予測—現値$4,436から約14%の上昇余地を示唆",
        "FRBの利下げ期待後退（実質金利上昇）—金利機会コスト増で短期的な下押し圧力になり得る"
      ],
      "top_news": [
        {
          "headline": "金が$4,436/ozで推移—地政学リスクプレミアムが年初来リターンの約12%分を占めると試算",
          "published": "2026-06-02",
          "comment": "世界情勢が不安定なときに金が買われる典型例。急上昇後は利益確定売りも出やすい",
          "source": "Capital.com",
          "tier": 2,
          "credibility": "MID",
          "corroborated_by": [],
          "materiality": "high",
          "direction": "bullish",
          "url": "https://capital.com/en-int/market-updates/gold-price-forecast-02-06-2026"
        },
        {
          "headline": "JPMorganが2026年Q4の金平均価格を$5,055/ozと予測—地政学リスクと中央銀行買いが主因",
          "published": "2026-05-01",
          "comment": "大手銀行による強気予測は方向感の参考になるが、外れるリスクも常に存在する",
          "source": "J.P. Morgan",
          "tier": 1,
          "credibility": "HIGH",
          "corroborated_by": [],
          "materiality": "mid",
          "direction": "bullish",
          "url": "https://www.jpmorgan.com/insights/global-research/commodities/gold-prices"
        },
        {
          "headline": "主要中央銀行が2026年も金を約755トン購入する見込み—ドル資産分散の動きが継続",
          "published": "2025-12-10",
          "comment": "各国中央銀行の継続的な買い付けが金価格の底堅さを維持する構造的な要因となっている",
          "source": "World Gold Council",
          "tier": 1,
          "credibility": "HIGH",
          "corroborated_by": [],
          "materiality": "mid",
          "direction": "bullish",
          "url": "https://www.gold.org/goldhub/research/gold-outlook-2026"
        }
      ]
    },
    {
      "name": "原油",
      "ticker": "CL=F",
      "bias": "BULLISH",
      "conviction": "HIGH",
      "rationale": "WTI原油は$95.68/バレルと3日連続上昇。2月28日開始の米・イスラエル対イラン軍事行動でホルムズ海峡が閉鎖され、世界の石油供給の約20%が途絶。IEAは「史上最大の供給途絶」と認定し、Vitol CEOは累積生産損失が10億バレルに達すると警告。米国の原油在庫は6週連続減少（直近週-797万バレル）。戦争開始前の$72から現在$95まで約32%上昇（ピーク時は$120近く）。米・イラン和平交渉は不透明で、短期的な供給回復は見込みにくい。HIGH conviction。",
      "catalysts": [
        "ホルムズ海峡閉鎖継続—世界石油供給の約20%が途絶、IEAが「史上最大の供給途絶」と認定",
        "米国原油在庫が6週連続で減少（直近週-797万バレル）—需給タイト感が一段と強まる",
        "Vitol CEO：戦争による累積生産損失が10億バレルに達する見込み",
        "米・イラン和平交渉の不透明感—6月初旬にイランが交渉中断・封鎖継続を示唆"
      ],
      "top_news": [
        {
          "headline": "WTI原油が$95台で3日続伸—ホルムズ海峡閉鎖継続とイランの交渉中断が供給不安を強化",
          "published": "2026-06-03",
          "comment": "石油の通り道が塞がれたままで、価格が高止まりしやすい状況が続いている",
          "source": "fxdailyreport.com",
          "tier": 3,
          "credibility": "MID",
          "corroborated_by": ["Reuters", "Bloomberg"],
          "materiality": "high",
          "direction": "bullish",
          "url": "https://fxdailyreport.com/wti-crude-oil-price-analysis-for-june-1-2026/"
        },
        {
          "headline": "IEAが2026年イラン戦争を「史上最大の石油供給途絶」と認定—ホルムズ封鎖で世界供給の20%が消失",
          "published": "2026-04-21",
          "comment": "1970年代の石油危機を超える規模の供給ショック。インフレや景気後退リスクに直結する",
          "source": "CNBC",
          "tier": 2,
          "credibility": "HIGH",
          "corroborated_by": ["Reuters", "Bloomberg"],
          "materiality": "high",
          "direction": "bullish",
          "url": "https://www.cnbc.com/2026/04/21/oil-price-iran-war-middle-east.html"
        },
        {
          "headline": "米国原油在庫が6週連続で減少—直近週は約797万バレル減と需給タイト感が一段と強まる",
          "published": "2026-06-03",
          "comment": "在庫が減り続けるということは需要に供給が追いついていない状態を示している",
          "source": "CME Group",
          "tier": 1,
          "credibility": "HIGH",
          "corroborated_by": [],
          "materiality": "mid",
          "direction": "bullish",
          "url": "https://www.cmegroup.com/markets/energy/crude-oil/light-sweet-crude.quotes.html"
        }
      ]
    },
    {
      "name": "ドル円",
      "ticker": "USDJPY",
      "bias": "BEARISH",
      "conviction": "MID",
      "rationale": "ドル円は159.9円（6月4日木曜日）で心理的節目160円に接近し介入警戒ゾーンに滞在。日本当局は4月28日〜5月27日の1ヶ月間に約11.7兆円（736億ドル）の史上最大規模の介入を実施済み。日銀は6月15-16日会合で0.75%→1.0%への利上げが市場織り込み78-81%（Reuters調査の約2/3のエコノミストが予測）。利上げ実施なら日米金利差縮小→円高方向。FRBは6月16-17日に据え置き見込み（96%）。中期的にはドル安・円高方向への転換リスクが高まっている。",
      "catalysts": [
        "日銀6月15-16日会合—0.75%→1.0%利上げ確率78-81%、実施なら日米金利差縮小で円高転換",
        "160円接近で財務省・日銀による追加介入リスク—4月28日〜5月27日に11.7兆円投入済み",
        "FRBが6月16-17日に金利据え置き見込み（96%）—日米金利差縮小ペースは利上げ次第",
        "中東情勢によるエネルギー輸入増→日本の経常収支悪化→円安圧力との綱引き"
      ],
      "top_news": [
        {
          "headline": "ドル円が159.9円と160円の介入警戒ラインに接近—当局が「必要に応じ措置を講じる」と再警告",
          "published": "2026-06-04",
          "comment": "160円を超えると日本政府が再介入する可能性が高く、急な円高リスクが潜む水準",
          "source": "CNBC",
          "tier": 2,
          "credibility": "HIGH",
          "corroborated_by": ["Reuters"],
          "materiality": "high",
          "direction": "bearish",
          "url": "https://www.cnbc.com/2026/05/07/japan-yen-intervention-boj-rate-gap-currency-pressure.html"
        },
        {
          "headline": "日銀副総裁が追加利上げへの継続コミットを表明—中東情勢次第でタイミング調整の余地残す",
          "published": "2026-06-02",
          "comment": "日銀が利上げ路線を維持している限り、長期的には円高圧力が高まりやすい",
          "source": "cryptobriefing.com",
          "tier": 3,
          "credibility": "MID",
          "corroborated_by": ["Reuters"],
          "materiality": "high",
          "direction": "bearish",
          "url": "https://cryptobriefing.com/yen-intervention-risk-boj-rate-hike/"
        },
        {
          "headline": "日本当局が4月28日〜5月27日に約11.7兆円（736億ドル）の為替介入—史上最大規模を動員",
          "published": "2026-05-27",
          "comment": "これほど大規模な介入をしても160円を防げていないことが、円安の根深さを示している",
          "source": "CNBC",
          "tier": 2,
          "credibility": "HIGH",
          "corroborated_by": ["Reuters"],
          "materiality": "mid",
          "direction": "bearish",
          "url": "https://www.cnbc.com/2026/05/01/yen-steadies-after-japan-intervention-traders-brace-for-more-action.html"
        }
      ]
    },
    {
      "name": "ユーロドル",
      "ticker": "EURUSD",
      "bias": "BULLISH",
      "conviction": "MID",
      "rationale": "ユーロドルは6月3日に1.1597（6月1日ECBリファレンス1.1646から小幅下落）。ECBが近く25bpの利上げを実施する見込み（市場織り込み95%）で、ユーロ圏5月インフレは3.2%（2.5年ぶり高水準）がその根拠。過去12ヶ月で+1.58%の上昇トレンド継続中。GoldmanSachsの年末目標は1.25、JPMorganは1.22と中期的な上昇継続を見込む。FRBが据え置き継続（利下げ後退）によりドルの上値が抑えられ、ECBの引き締めがユーロを相対優位に保つ構図。",
      "catalysts": [
        "ECBが近く25bp追加利上げ実施見込み（市場織り込み95%）—ユーロ圏5月インフレ3.2%が根拠",
        "FRBが6月16-17日会合で据え置き（96%）—ECBの引き締めがFRBより積極的でユーロ支援",
        "Goldman SachsのEUR/USD年末目標1.25、JPMorgan目標1.22—中期的な上昇余地を示す",
        "中東紛争によるエネルギー高騰がユーロ圏インフレ圧力を維持—ECBの引き締め継続の要因"
      ],
      "top_news": [
        {
          "headline": "ECBが6月に25bpの追加利上げを実施する確率95%—ユーロ圏5月インフレが3.2%と2.5年ぶり高水準",
          "published": "2026-05-30",
          "comment": "ECBが利上げを続ける理由がある限り、ユーロに対する買い支えが期待しやすい",
          "source": "ECB",
          "tier": 1,
          "credibility": "HIGH",
          "corroborated_by": ["Reuters", "Bloomberg"],
          "materiality": "high",
          "direction": "bullish",
          "url": "https://www.ecb.europa.eu/stats/policy_and_exchange_rates/euro_reference_exchange_rates/html/index.en.html"
        },
        {
          "headline": "ユーロドルが1.1597で推移—Goldman年末目標1.25、過去12ヶ月で+1.58%の上昇トレンド継続",
          "published": "2026-06-03",
          "comment": "長期的なユーロ高トレンドは継続中だが、短期的には上下に振れやすい水準でもある",
          "source": "Trading Economics",
          "tier": 2,
          "credibility": "MID",
          "corroborated_by": ["ECB"],
          "materiality": "mid",
          "direction": "bullish",
          "url": "https://tradingeconomics.com/euro-area/currency"
        }
      ]
    },
    {
      "name": "ビットコイン",
      "ticker": "BTC-USD",
      "bias": "BEARISH",
      "conviction": "MID",
      "rationale": "BTCは6月1日の$72,145から6月3日に$66,965まで約7.2%急落、日中は$65,400を試す場面も。Strategyが約4年ぶりにBTCを売却したことで大口機関投資家の撤退懸念が台頭。5月は現物ETFから月間$24億（年間最悪の月間流出額）が流出し、6月3日の仮想通貨恐怖&強欲指数は11（極度の恐怖）。2025年10月の高値$126,200から現在は約47%下落済み。日銀利上げ期待によるリスクオフ拡大と円キャリートレード巻き戻しもBTC売りを加速させた。短期は弱気継続が見込まれる。",
      "catalysts": [
        "Strategyが約4年ぶりにBTCを売却—大口機関投資家の撤退懸念が拡大し相場心理が悪化",
        "現物BTC ETFから5月に月間$24億が流出—年間最悪の月間流出額を記録し需給が悪化",
        "仮想通貨恐怖&強欲指数が11（極度の恐怖）—投資家心理が極限まで冷え込んでいる",
        "日銀利上げ期待によるリスクオフ拡大—円キャリートレード巻き戻しがBTC売りに波及"
      ],
      "top_news": [
        {
          "headline": "BTCが6月1日の$72,145から6月3日に$66,965まで急落—Strategyの4年ぶり売却で撤退懸念",
          "published": "2026-06-03",
          "comment": "大口機関投資家がBTCを売り始めたというニュースは相場心理を悪化させやすい",
          "source": "Bitcoin Foundation",
          "tier": 3,
          "credibility": "MID",
          "corroborated_by": ["CoinDesk"],
          "materiality": "high",
          "direction": "bearish",
          "url": "https://bitcoinfoundation.org/news/bitcoin/why-is-crypto-crashing-bitcoin-falls-below-70k-after-strategys-first-btc-sale-in-nearly-four-years/"
        },
        {
          "headline": "仮想通貨現物ETFが5月に月間$24億の過去最大流出—機関投資家がリスク資産を圧縮",
          "published": "2026-06-01",
          "comment": "ETFから資金が出続けていると、BTCを買い支える勢力が弱まることを意味する",
          "source": "CoinDesk",
          "tier": 2,
          "credibility": "HIGH",
          "corroborated_by": ["Bitcoin Foundation"],
          "materiality": "high",
          "direction": "bearish",
          "url": "https://www.coindesk.com/price/bitcoin"
        },
        {
          "headline": "仮想通貨恐怖&強欲指数が11（極度の恐怖）—BTCは2025年10月の$126,200高値から約47%下落",
          "published": "2026-06-03",
          "comment": "極度の恐怖は時にバリュー買いの機会でもあるが、トレンド転換の確認が先決",
          "source": "stealthex.io",
          "tier": 3,
          "credibility": "LOW",
          "corroborated_by": [],
          "materiality": "mid",
          "direction": "bearish",
          "url": "https://stealthex.io/blog/why-is-bitcoin-dropping/"
        }
      ]
    }
  ],
  "discarded": [
    {
      "headline": "Peter SchiffがBTCの$20,000への急落を予測",
      "reason": "単一の著名な弱気論者の予測で信頼性LOW。過去も外れが多く情報価値が低い"
    },
    {
      "headline": "各種AI予測ツールによるBTC価格予測（$81,349等）",
      "reason": "自動生成予測で一次ソースなし、tier4/LOW相当のため除外"
    },
    {
      "headline": "Long ForecastやWalletInvestorによる自動モデルの金価格月次予測",
      "reason": "自動予測モデルで一次ソースなし、tier4相当のため除外"
    },
    {
      "headline": "BTC機関投資家の撤退フォーシャドウが予測する暴落シナリオ（beincrypto）",
      "reason": "単一tier3メディアの予測記事で独立検証なし、LOW信頼のため除外"
    }
  ]
}
